setup.py
car/__init__.py
car/code1.py
car/code2.py
huawei.egg-info/PKG-INFO
huawei.egg-info/SOURCES.txt
huawei.egg-info/dependency_links.txt
huawei.egg-info/top_level.txt