Metadata-Version: 1.0
Name: huawei
Version: 7.7.7
Summary: 蒋付帮
Home-page: https://github.com/jiangfubang
Author: Jiang Fubang
Author-email: luckybang@163.com
License: MIT Licence
Keywords: pip,utils
Platform: any
